geode_background/__init__.py
geode_background/__init__.pyi
geode_background/brep_background.py
geode_background/brep_background.pyi
geode_background/common_background.py
geode_background/common_background.pyi
geode_background/py.typed
geode_background/solid_background.py
geode_background/solid_background.pyi
geode_background/surface_background.py
geode_background/surface_background.pyi
geode_background/lib64/__init__.pyi
geode_background/lib64/geode_background_py_brep.cpython-312-x86_64-linux-gnu.so
geode_background/lib64/geode_background_py_brep.pyi
geode_background/lib64/geode_background_py_common.cpython-312-x86_64-linux-gnu.so
geode_background/lib64/geode_background_py_common.pyi
geode_background/lib64/geode_background_py_solid.cpython-312-x86_64-linux-gnu.so
geode_background/lib64/geode_background_py_solid.pyi
geode_background/lib64/geode_background_py_surface.cpython-312-x86_64-linux-gnu.so
geode_background/lib64/geode_background_py_surface.pyi
geode_background/lib64/libGeode-Background_brep.so
geode_background/lib64/libGeode-Background_common.so
geode_background/lib64/libGeode-Background_line.so
geode_background/lib64/libGeode-Background_solid.so
geode_background/lib64/libGeode-Background_surface.so
geode_background-9.9.6.dist-info/METADATA
geode_background-9.9.6.dist-info/WHEEL
geode_background-9.9.6.dist-info/top_level.txt
geode_background-9.9.6.dist-info/RECORD
