Metadata-Version: 2.4
Name: Geode-Background
Version: 9.9.6
Summary: Geode-solutions OpenGeode module for building background meshes
Author-email: Geode-solutions <contact@geode-solutions.com>
License: Proprietary
Requires-Python: <3.13,>=3.9
Requires-Dist: geode-common==33.*,>=33.16.4
Requires-Dist: opengeode-core==15.*,>=15.30.16
